densitysplit-0.2.3.data/purelib/densitysplit/__init__.py
densitysplit-0.2.3.data/purelib/densitysplit/box/Makefile
densitysplit-0.2.3.data/purelib/densitysplit/box/__init__.py
densitysplit-0.2.3.data/purelib/densitysplit/box/split.py
densitysplit-0.2.3.data/purelib/densitysplit/box/utilities.py
densitysplit-0.2.3.data/purelib/densitysplit/box/bin/.gitignore
densitysplit-0.2.3.data/purelib/densitysplit/box/bin/tophat_filter.exe
densitysplit-0.2.3.data/purelib/densitysplit/box/fortran/Makefile
densitysplit-0.2.3.data/purelib/densitysplit/box/fortran/procedures.f90
densitysplit-0.2.3.data/purelib/densitysplit/box/fortran/procedures.mod
densitysplit-0.2.3.data/purelib/densitysplit/box/fortran/tophat_filter.f90
densitysplit-0.2.3.data/purelib/densitysplit/survey/.gitignore
densitysplit-0.2.3.data/purelib/densitysplit/survey/Makefile
densitysplit-0.2.3.data/purelib/densitysplit/survey/__init__.py
densitysplit-0.2.3.data/purelib/densitysplit/survey/cosmology.py
densitysplit-0.2.3.data/purelib/densitysplit/survey/split.py
densitysplit-0.2.3.data/purelib/densitysplit/survey/utilities.py
densitysplit-0.2.3.data/purelib/densitysplit/survey/__pycache__/__init__.cpython-38.pyc
densitysplit-0.2.3.data/purelib/densitysplit/survey/__pycache__/cosmology.cpython-38.pyc
densitysplit-0.2.3.data/purelib/densitysplit/survey/__pycache__/split.cpython-38.pyc
densitysplit-0.2.3.data/purelib/densitysplit/survey/__pycache__/utilities.cpython-38.pyc
densitysplit-0.2.3.data/purelib/densitysplit/survey/bin/.gitignore
densitysplit-0.2.3.data/purelib/densitysplit/survey/bin/gaussian_filter.exe
densitysplit-0.2.3.data/purelib/densitysplit/survey/bin/tophat_filter.exe
densitysplit-0.2.3.data/purelib/densitysplit/survey/fortran/.gitignore
densitysplit-0.2.3.data/purelib/densitysplit/survey/fortran/Makefile
densitysplit-0.2.3.data/purelib/densitysplit/survey/fortran/gaussian_filter.f90
densitysplit-0.2.3.data/purelib/densitysplit/survey/fortran/gaussian_filter.o
densitysplit-0.2.3.dist-info/LICENSE
densitysplit-0.2.3.dist-info/METADATA
densitysplit-0.2.3.dist-info/WHEEL
densitysplit-0.2.3.dist-info/top_level.txt
densitysplit-0.2.3.dist-info/RECORD
