Metadata-Version: 2.1
Name: densitysplit
Version: 0.2.3
Summary: Redshift-space distortions with split densities
Home-page: https://github.com/epaillas/densitysplit
Author: Enrique Paillas
Author-email: epaillas@astro.puc.cl
License: MIT
Platform: UNKNOWN
Classifier: License :: OSI Approved :: MIT License
Classifier: Programming Language :: Python
Classifier: Programming Language :: Python :: 3
Classifier: Programming Language :: Python :: 3.6
Classifier: Programming Language :: Python :: Implementation :: CPython
Classifier: Programming Language :: Python :: Implementation :: PyPy
Requires-Python: >=3.6.0
